sqlmodel_repository/__init__.py
sqlmodel_repository/base_repository.py
sqlmodel_repository/entity.py
sqlmodel_repository/exceptions.py
sqlmodel_repository/logger.py
sqlmodel_repository/repository.py
sqlmodel_repository-2.0.1.dist-info/LICENSE
sqlmodel_repository-2.0.1.dist-info/METADATA
sqlmodel_repository-2.0.1.dist-info/WHEEL
sqlmodel_repository-2.0.1.dist-info/RECORD
