Metadata-Version: 2.1
Name: sqlmodel-repository
Version: 2.0.1
Summary: Repository pattern implementation for SQLModel (SQLAlchemy)
License: MIT
Author: Jonas Scholl
Author-email: jonas@code-specialist.com
Requires-Python: >=3.9,<4.0
Classifier: License :: OSI Approved :: MIT License
Classifier: Programming Language :: Python :: 3
Classifier: Programming Language :: Python :: 3.9
Classifier: Programming Language :: Python :: 3.10
Classifier: Programming Language :: Python :: 3.11
Requires-Dist: sqlmodel (>=0.0.8,<0.0.9)
Requires-Dist: structlog (>=23.1.0,<24.0.0)
